meshoptimizer/__init__.py
meshoptimizer-0.1.0.dist-info/LICENSE
meshoptimizer-0.1.0.dist-info/METADATA
meshoptimizer-0.1.0.dist-info/WHEEL
meshoptimizer-0.1.0.dist-info/top_level.txt
meshoptimizer-0.1.0.dist-info/RECORD
